.travis.yml
AUTHORS
ChangeLog
LICENSE
MANIFEST.in
README.rst
requirements.txt
setup.cfg
setup.py
excel2img/__init__.py
excel2img/excel2img.py
excel2img.egg-info/PKG-INFO
excel2img.egg-info/SOURCES.txt
excel2img.egg-info/dependency_links.txt
excel2img.egg-info/not-zip-safe
excel2img.egg-info/pbr.json
excel2img.egg-info/requires.txt
excel2img.egg-info/top_level.txt
tests/test.xlsx
tests/test_excel2img.py